pyitu/__init__.py
pyitu/fixed.py
pyitu/p676.py
pyitu/p835.py
pyitu/p838.py
pyitu/tooling.py
pyitu-0.1.10.dist-info/METADATA
pyitu-0.1.10.dist-info/WHEEL
pyitu-0.1.10.dist-info/licenses/LICENSE
pyitu-0.1.10.dist-info/RECORD
