Metadata-Version: 2.4
Name: pyitu
Version: 0.1.10
Summary: A collection of ITU based propagation models
Project-URL: Homepage, https://github.com/richardtjornhammar/pyitu
Project-URL: Issues, https://github.com/richardtjornhammar/pyitu
Author-email: Richard Tjörnhammar <richard.tjornhammar@gmail.com>
License-Expression: Apache-2.0
License-File: LICENSE
Classifier: License :: OSI Approved :: Apache Software License
Classifier: Operating System :: OS Independent
Classifier: Programming Language :: Python :: 3.11
Requires-Python: >=3.11
